bkmeans/__init__.py
bkmeans/bkm_compact.py
bkmeans/bkmeans.py
bkmeans/bkmeans_test.py
bkmeans/bkmeansw.py
bkmeans-1.3.dist-info/LICENSE
bkmeans-1.3.dist-info/METADATA
bkmeans-1.3.dist-info/WHEEL
bkmeans-1.3.dist-info/top_level.txt
bkmeans-1.3.dist-info/RECORD
