Metadata-Version: 2.1
Name: bkmeans
Version: 1.3
Summary: The breathing k-means algorithm
Home-page: https://github.com/gittar/bkmeans
Author: Bernd Fritzke
Author-email: fritzke@web.de
License: MIT
Platform: UNKNOWN
Classifier: License :: OSI Approved :: MIT License
Classifier: Programming Language :: Python
Classifier: Programming Language :: Python :: 3
Classifier: Programming Language :: Python :: 3.7
Classifier: Programming Language :: Python :: Implementation :: CPython
Classifier: Topic :: Scientific/Engineering
Classifier: Topic :: Scientific/Engineering :: Artificial Intelligence
Requires-Python: >=3.7.0
License-File: LICENSE
Requires-Dist: numpy
Requires-Dist: scikit-learn (>=1.2.2)
Requires-Dist: scipy
